mysodexo/__init__.py
mysodexo/api.py
mysodexo/cli.py
mysodexo/constants.py
mysodexo/sodexows.mo2o.com_client-android.crt.pem
mysodexo/sodexows.mo2o.com_client-android.key.pem
sodexo-20221022.dist-info/LICENSE
sodexo-20221022.dist-info/METADATA
sodexo-20221022.dist-info/WHEEL
sodexo-20221022.dist-info/entry_points.txt
sodexo-20221022.dist-info/top_level.txt
sodexo-20221022.dist-info/RECORD
