Metadata-Version: 2.1
Name: sodexo
Version: 20221022
Summary: Mysodexo Python client
Home-page: https://github.com/AndreMiras/mysodexo
Author: Andre Miras
License-File: LICENSE
Requires-Dist: mysodexo
